pythonUtilitiesProject/__init__.py
pythonUtilitiesProject/utilities/__init__.py
pythonUtilitiesProject/utilities/utilities.py
tests/__init__.py
tests/utilities/__init__.py
tests/utilities/utilites_test.py
pythonUtilitiesProject-0.1.3.dist-info/METADATA
pythonUtilitiesProject-0.1.3.dist-info/WHEEL
pythonUtilitiesProject-0.1.3.dist-info/top_level.txt
pythonUtilitiesProject-0.1.3.dist-info/RECORD
