Metadata-Version: 2.1
Name: pythonUtilitiesProject
Version: 0.1.3
Summary: Utilities used for the german supermarket web scrapping project
Classifier: Programming Language :: Python :: 3
Requires-Python: >=3.6
